ddcore/Cache.py
ddcore/Config.py
ddcore/Decorators.py
ddcore/GeoServiceUtil.py
ddcore/Hash.py
ddcore/RedisStore.py
ddcore/SendgridUtil.py
ddcore/Serializers.py
ddcore/Utilities.py
ddcore/Validator.py
ddcore/__init__.py
ddcore/admin.py
ddcore/apps.py
ddcore/constants.py
ddcore/exception.py
ddcore/logconst.py
ddcore/logformat.py
ddcore/response.py
ddcore/settings.py
ddcore/tasks.py
ddcore/uuids.py
ddcore/aws/CloudFrontUtil.py
ddcore/aws/ESUtil.py
ddcore/aws/S3Util.py
ddcore/aws/SMUtil.py
ddcore/aws/SQSUtil.py
ddcore/aws/__init__.py
ddcore/aws/tests/__init__.py
ddcore/aws/tests/test_aws_CloudFrontUtil.py
ddcore/aws/tests/test_aws_ESUtil.py
ddcore/aws/tests/test_aws_S3Util.py
ddcore/aws/tests/test_aws_SMUtil.py
ddcore/aws/tests/test_aws_SQSUtil.py
ddcore/geoip/__init__.py
ddcore/middleware/__init__.py
ddcore/middleware/django_logging_middleware.py
ddcore/middleware/django_request_id_middleware.py
ddcore/migrations/0001_initial.py
ddcore/migrations/0002_temporaryfile_upload_type.py
ddcore/migrations/__init__.py
ddcore/models/Accounts.py
ddcore/models/Address.py
ddcore/models/Attachment.py
ddcore/models/Base.py
ddcore/models/Comment.py
ddcore/models/Complaint.py
ddcore/models/Newsletter.py
ddcore/models/Phone.py
ddcore/models/Rating.py
ddcore/models/SocialLink.py
ddcore/models/View.py
ddcore/models/__init__.py
ddcore/models/tests/__init__.py
ddcore/models/tests/test_models_Accounts.py
ddcore/models/tests/test_models_Address.py
ddcore/models/tests/test_models_Attachment.py
ddcore/models/tests/test_models_Base.py
ddcore/models/tests/test_models_Comment.py
ddcore/models/tests/test_models_Complaint.py
ddcore/models/tests/test_models_Newsletter.py
ddcore/models/tests/test_models_Phone.py
ddcore/models/tests/test_models_Rating.py
ddcore/models/tests/test_models_SociaLink.py
ddcore/models/tests/test_models_View.py
ddcore/tests/__init__.py
ddcore/tests/test_Cache.py
ddcore/tests/test_Config.py
ddcore/tests/test_Decorators.py
ddcore/tests/test_Exception.py
ddaemon_core_python-0.5.2.dist-info/LICENSE
ddaemon_core_python-0.5.2.dist-info/METADATA
ddaemon_core_python-0.5.2.dist-info/WHEEL
ddaemon_core_python-0.5.2.dist-info/top_level.txt
ddaemon_core_python-0.5.2.dist-info/RECORD
