Metadata-Version: 2.2
Name: ddaemon-core-python
Version: 0.5.2
Summary: DDaemon Core.
Home-page: https://github.com/asuvorov/ddaemon-core-python/
Author: Artem Suvorov
Author-email: artem.suvorov@gmail.com
License: GPLv3 License
Classifier: Development Status :: 4 - Beta
Classifier: Environment :: Console
Classifier: Environment :: Plugins
Classifier: Framework :: Django
Classifier: Framework :: Django :: 4.2
Classifier: Framework :: Pytest
Classifier: Intended Audience :: Developers
Classifier: Intended Audience :: Information Technology
Classifier: License :: OSI Approved :: GNU General Public License v3 (GPLv3)
Classifier: Natural Language :: English
Classifier: Operating System :: Microsoft :: Windows
Classifier: Operating System :: POSIX
Classifier: Operating System :: POSIX :: Linux
Classifier: Programming Language :: Python :: 3
Classifier: Programming Language :: Python :: 3.12
Classifier: Topic :: Scientific/Engineering
Classifier: Topic :: Security
License-File: LICENSE
Requires-Dist: Django==4.2.13
Requires-Dist: boto3==1.34.122
Requires-Dist: beautifulsoup4==4.12.3
Requires-Dist: bumpversion==0.6.0
Requires-Dist: coverage==7.5.0
Requires-Dist: django-annoying==0.10.6
Requires-Dist: django-ckeditor==6.7.1
Requires-Dist: django-countries==7.6.1
Requires-Dist: django-extensions==3.2.3
Requires-Dist: django-ipware==4.0.2
Requires-Dist: django-phonenumbers==1.0.1
Requires-Dist: django-phonenumber-field==7.3.0
Requires-Dist: django-storages==1.14.3
Requires-Dist: geoip2>=3.0.0
Requires-Dist: ipython==8.18.1
Requires-Dist: json-log-formatter==1.1
Requires-Dist: mysqlclient==2.2.4
Requires-Dist: pendulum==3.0.0
Requires-Dist: pep257==0.7.0
Requires-Dist: pep8==1.7.1
Requires-Dist: pycodestyle==2.11.1
Requires-Dist: pydocstyle==6.3.0
Requires-Dist: pyflakes==3.2.0
Requires-Dist: pylint==3.1.0
Requires-Dist: pylint-django==2.5.5
Requires-Dist: pymemcache==4.0.0
Requires-Dist: pytest==7.4.0
Requires-Dist: pytz==2024.1
Requires-Dist: pyyaml==6.0.1
Requires-Dist: python-decouple==3.8
Requires-Dist: python-memcached==1.62
Requires-Dist: requests==2.31.0
Requires-Dist: simplejson==3.19.2
Requires-Dist: termcolor==2.4.0
Dynamic: author
Dynamic: author-email
Dynamic: classifier
Dynamic: description-content-type
Dynamic: home-page
Dynamic: license
Dynamic: requires-dist
Dynamic: summary
